namesex_light/__init__.py
namesex_light/namesex_light.py
namesex_light/test_namesex_light.py
namesex_light/testdata.py
namesex_light/data/testdata.csv
namesex_light/model/logic_light.pickle
namesex_light-0.2.1.dist-info/DESCRIPTION.rst
namesex_light-0.2.1.dist-info/METADATA
namesex_light-0.2.1.dist-info/RECORD
namesex_light-0.2.1.dist-info/WHEEL
namesex_light-0.2.1.dist-info/metadata.json
namesex_light-0.2.1.dist-info/top_level.txt
