Metadata-Version: 2.0
Name: namesex-light
Version: 0.2.1
Summary: A lightweight gender classifier for Chinese given names
Home-page: https://github.com/hsinmin/namesex_light
Author: Hsin-Min Lu, Yu-Lun Li, Chi-Yu Lin
Author-email: luim@ntu.edu.tw
License: UNKNOWN
Keywords: classify_sex Chinese_given_name
Platform: UNKNOWN
Classifier: Development Status :: 4 - Beta
Classifier: Intended Audience :: Science/Research
Classifier: Topic :: Scientific/Engineering :: Artificial Intelligence
Classifier: License :: OSI Approved :: GNU General Public License v3 or later (GPLv3+)
Classifier: Programming Language :: Python :: 3
Classifier: Programming Language :: Python :: 3.4
Classifier: Programming Language :: Python :: 3.5
Classifier: Programming Language :: Python :: 3.6
Classifier: Programming Language :: Python :: 3.7
Requires-Dist: numpy
